aftershocks.py
aftershocks-0.1.0.data/scripts/aftershocks.py
aftershocks-0.1.0.dist-info/METADATA
aftershocks-0.1.0.dist-info/RECORD
aftershocks-0.1.0.dist-info/WHEEL
aftershocks-0.1.0.dist-info/top_level.txt
