Metadata-Version: 2.1
Name: aftershocks
Version: 0.1.0
Summary: Plot recent earthquakes in Japan by region
Home-page: http://github.com/juseg/aftershocks
Author: Julien Seguinot
Author-email: seguinot@vaw.baug.ethz.ch
License: gpl-3.0
Platform: UNKNOWN
Requires-Dist: matplotlib
Requires-Dist: pandas
